kata_anagrams_weabreu/__init__.py
kata_anagrams_weabreu/anagrams.py
kata_anagrams_weabreu-1.1.0.dist-info/METADATA
kata_anagrams_weabreu-1.1.0.dist-info/WHEEL
kata_anagrams_weabreu-1.1.0.dist-info/licenses/LICENSE
kata_anagrams_weabreu-1.1.0.dist-info/RECORD
