Metadata-Version: 2.1
Name: kata_anagrams_weabreu
Version: 1.1.0
Summary: Library to solve Kata Anagram
Project-URL: Homepage, https://github.com/weabreu16/kata_anagrams
Project-URL: Bug Tracker, https://github.com/weabreu16/kata_anagrams/issues
Author-email: William Abreu <weabreu16@gmail.com>
License: Copyright (c) 2022 weabreu
License-File: LICENSE
Classifier: License :: OSI Approved :: MIT License
Classifier: Operating System :: OS Independent
Classifier: Programming Language :: Python :: 3
Requires-Python: >=3.7
